catclass/__init__.py
catclass/generator.py
catclass-0.1.3.dist-info/LICENSE
catclass-0.1.3.dist-info/METADATA
catclass-0.1.3.dist-info/WHEEL
catclass-0.1.3.dist-info/top_level.txt
catclass-0.1.3.dist-info/RECORD
