Metadata-Version: 2.1
Name: catclass
Version: 0.1.3
Summary: A robust framework for generating synthetic categorical datasets for evaluation or testing purposes.
Author: Miha Malenšek
License: Copyright (c) 2018 The Python Packaging Authority
Project-URL: Homepage, https://github.com/98MM/msc_cc
Project-URL: Repository, https://github.com/98MM/msc_cc
Keywords: synthetic datasets,data generation,categorical data
Classifier: Development Status :: 4 - Beta
Classifier: Intended Audience :: Developers
Classifier: Programming Language :: Python :: 3.8
Classifier: Programming Language :: Python :: 3.9
Classifier: Programming Language :: Python :: 3.10
Classifier: Programming Language :: Python :: 3.11
Classifier: Programming Language :: Python :: 3.12
Requires-Python: >=3.8
License-File: LICENSE
Requires-Dist: numpy
Requires-Dist: scipy
Requires-Dist: scikit-learn
Requires-Dist: typing
